pyewsclient
