Metadata-Version: 1.1
Name: PyEwsClient
Version: 1.1
Summary: Microsoft Office 365 EWS (Exchange Web Services) Client Library
Home-page: https://github.com/greenpau/PyEwsClient
Author: Paul Greenberg
Author-email: paul@greenberg.pro
License: GPLv3
Download-URL: http://pypi.python.org/packages/source/P/PyEwsClient/PyEwsClient-1.1.tar.gz
Platform: any
Classifier: Development Status :: 4 - Beta
Classifier: Programming Language :: Python
Classifier: Programming Language :: Python :: 3
Classifier: Programming Language :: Python :: 3.0
Classifier: Programming Language :: Python :: 3.1
Classifier: Programming Language :: Python :: 3.2
Classifier: Programming Language :: Python :: 3.3
Classifier: Programming Language :: Python :: 3.4
Classifier: Operating System :: OS Independent
Classifier: Topic :: Communications :: Email
Classifier: Topic :: Communications :: Email :: Address Book
Classifier: Topic :: Communications :: Email :: Email Clients (MUA)
Classifier: Topic :: Software Development :: User Interfaces
Classifier: Intended Audience :: End Users/Desktop
Classifier: Intended Audience :: Developers
Classifier: Intended Audience :: System Administrators
Classifier: License :: OSI Approved :: GNU General Public License v3 (GPLv3)
Classifier: License :: OSI Approved :: GNU General Public License v3 or later (GPLv3+)
